celery_persistent_revokes/__init__.py
celery_persistent_revokes/admin.py
celery_persistent_revokes/apps.py
celery_persistent_revokes/backends.py
celery_persistent_revokes/decorators.py
celery_persistent_revokes/helpers.py
celery_persistent_revokes/models.py
celery_persistent_revokes/settings.py
celery_persistent_revokes/signals.py
celery_persistent_revokes/utils.py
celery_persistent_revokes/migrations/0001_initial.py
celery_persistent_revokes/migrations/__init__.py
celery_persistent_revokes-1.0.1.dist-info/METADATA
celery_persistent_revokes-1.0.1.dist-info/RECORD
celery_persistent_revokes-1.0.1.dist-info/WHEEL
celery_persistent_revokes-1.0.1.dist-info/top_level.txt
