Metadata-Version: 2.1
Name: celery-persistent-revokes
Version: 1.0.1
Summary: Celery task revokes are stored on memory or on file. This packages makes possible to easely customize how your revokes are stored (Ex.: Database).
Home-page: https://github.com/hugobessa/celery-persistent-revokes
Author: Hugo Bessa
Author-email: hugo@vinta.com.br
License: UNKNOWN
Keywords: celery-persistent-revokes
Platform: UNKNOWN
Classifier: Development Status :: 3 - Alpha
Classifier: Framework :: Django :: 1.11
Classifier: Framework :: Django :: 2.0
Classifier: Intended Audience :: Developers
Classifier: License :: OSI Approved :: BSD License
Classifier: Natural Language :: English
Classifier: Programming Language :: Python :: 2
Classifier: Programming Language :: Python :: 2.7
Classifier: Programming Language :: Python :: 3
Classifier: Programming Language :: Python :: 3.4
Classifier: Programming Language :: Python :: 3.5
Classifier: Programming Language :: Python :: 3.6
Requires-Dist: django-model-utils (>=2.0)
